<?xml version="1.0"?>
<document>
  <Title><![CDATA[氣候變化 威脅兒童]]></Title>
  <Date><![CDATA[2017-05-25T00:00:00Z]]></Date>
  <Source><![CDATA[Sing Tao Daily (Hong Kong)]]></Source>
  <Language><![CDATA[Chinese, Traditional]]></Language>
  <Body><![CDATA[日前，世界氣象組織公布關於熱帶氣旋、龍捲風、閃電和雹暴等極端天氣和氣候事件造成最高死亡人數的「世界紀錄」，其中與強烈熱帶氣旋及龍捲風相關的最高死亡人數紀錄都在孟加拉發生：一九七○年十一月的強烈熱帶氣旋吹襲，直接導致三十萬人死亡；一九八九年四月發生的龍捲風則造成一千三百人死亡。
無可否認，愈趨加劇的氣候變化是人類面臨的重大危機，對脆弱的兒童來說，影響尤其深遠。氣候變化意味旱災和氾濫等情況愈見頻繁，影響糧食生產，兒童可能因缺乏食物而出現營養不良，情況嚴重的話更可能導致發展遲緩，甚至夭折。氣候變化亦令海平面上升，威脅島嶼國家及沿海地區的安全，並影響水資源的供應。
聯合國兒童基金會（UNICEF）在二○一五年發表的《除非我們現在就行動──氣候變化對兒童的影響》報告中指出，全球有五點三億名兒童在水災高危區中生活，而一點六億名兒童生活的地區則易受旱災侵襲。當中很多兒童都活在貧困 下，每天生活費不足港幣二十五元。大部分侵害兒童的疾病，如瘧疾、登革熱及痢疾等，在極端天氣下疫情亦見加劇，威脅兒童的生命。我們無法收回已排放到大氣層的溫室氣體，但我們有責任為兒童阻止全球繼續暖化，避免極端氣候事件進一步演變成災難。若不採取行動阻止氣候變化帶來的影響，我們的下一代將要繼承一個受嚴重破壞、不再適合居住的地球。
聯合國兒童基金香港委員會（UNICEF HK）培訓的三十四名青年使者將於本周六（五月二十七日）假樂富廣場A區平台舉辦「綠色為兒童」嘉年華。屆時將設互動攤位遊戲、體驗活動等，向公眾介紹氣候變化及兒童權利議題，有興趣的朋友可以到場參觀。網址：unicef.org.hk
本欄由聯合國兒童基金香港委員會撰寫。
]]></Body>
</document>
